{
  "users": [
    {
      "name": "Сергей",
      "surname": "Сергеевич",
      "phone": "+7(800) 555-3536",
      "type": 1,
      "id": 2
    },
    {
      "name": "Кирилл",
      "surname": "Кириллов",
      "phone": "+7(800) 555-3537",
      "type": 2,
      "id": 3
    },
    {
      "name": "Test",
      "surname": "Tests",
      "phone": "+1(111) 111-1111",
      "type": 3,
      "id": 4
    },
    {
      "name": "НадеюсьНаЭкзамене",
      "surname": "БудетЛегче",
      "phone": "+9(999) 999-9999",
      "type": 0,
      "id": 6
    },
    {
      "name": "Иван",
      "surname": "Иванов",
      "phone": "+7(800) 555-3535",
      "type": 0,
      "id": 7
    }
  ]
}